opt/__init__.py
opt/multi_objective/__init__.py
opt/single_objective/__init__.py
opt/single_objective/comb/__init__.py
opt/single_objective/comb/max_ones_count_problem/__init__.py
opt/single_objective/comb/max_ones_count_problem/command_line.py
opt/single_objective/comb/max_ones_count_problem/inputs/dimension_10.txt
opt/single_objective/comb/max_ones_count_problem/inputs/dimension_25.txt
opt/single_objective/comb/max_ones_count_problem/inputs/dimension_5.txt
opt/single_objective/comb/max_ones_count_problem/inputs/dimension_77.txt
opt/single_objective/comb/max_ones_count_problem/max_ones_count_problem.py
opt/single_objective/comb/max_ones_count_problem/max_ones_count_problem_bit_array_solution.py
opt/single_objective/comb/max_ones_count_problem/max_ones_count_problem_ilp_linopy.py
opt/single_objective/comb/max_ones_count_problem/max_ones_count_problem_int_solution.py
opt/single_objective/comb/max_ones_count_problem/outputs/to-do.txt
opt/single_objective/comb/max_ones_count_problem/solver.py
opt/single_objective/comb/max_ones_count_problem/test_integration_max_ones_count_problem_ga_bit_array_solution.py
opt/single_objective/comb/max_ones_count_problem/test_integration_max_ones_count_problem_ilp_linopy.py
opt/single_objective/comb/max_ones_count_problem/test_integration_max_ones_count_problem_te_bit_array_solution.py
opt/single_objective/comb/max_ones_count_problem/test_integration_max_ones_count_problem_vns_bit_array_solution_lsbi.py
opt/single_objective/comb/max_ones_count_problem/test_integration_max_ones_count_problem_vns_bit_array_solution_lsfi.py
opt/single_objective/comb/max_ones_count_problem/test_integration_max_ones_count_problem_vns_int_solution_lsbi.py
opt/single_objective/comb/max_ones_count_problem/test_integration_max_ones_count_problem_vns_int_solution_lsfi.py
opt/single_objective/comb/max_ones_count_problem/test_max_ones_count_problem.py
opt/single_objective/comb/max_ones_count_problem/test_max_ones_count_problem_bit_array_solution.py
universal_optimizer-0.2.0.dist-info/LICENSE
universal_optimizer-0.2.0.dist-info/METADATA
universal_optimizer-0.2.0.dist-info/NOTICE
universal_optimizer-0.2.0.dist-info/WHEEL
universal_optimizer-0.2.0.dist-info/RECORD
