Metadata-Version: 2.1
Name: universal-optimizer
Version: 0.2.0
Summary: Universal Optimizer Library
License: Apache 2.0
Author: Vladimir Filipovic
Author-email: vladofilipovic@hotmail.com
Requires-Python: >=3.11,<4.0
Classifier: License :: Other/Proprietary License
Classifier: Programming Language :: Python :: 3
Classifier: Programming Language :: Python :: 3.11
Classifier: Programming Language :: Python :: 3.12
Requires-Dist: bitstring (>=4.1.1,<5.0.0)
Requires-Dist: coverage (>=7.4.0,<8.0.0)
Requires-Dist: gurobipy (>=10.0.3,<11.0.0)
Requires-Dist: linopy (==0.3.0)
Requires-Dist: networkx (>=3.3,<4.0)
Requires-Dist: pathlib (>=1.0.1,<2.0.0)
